{
  "surgery": {
    "acl": {
      "days": [
        null,
        {
          "end": 75,
          "message": "The first day after surgery is hard, but today marks the beginning of your recovery journey. Please make sure to ice and elevate your leg today. Eat as well as you can. Good nutrition will help the recovery time.",
          "start": 70
        },
        {
          "end": 75,
          "message": "Over the next week, we will be working towards small controlled movements of the knee. This may be painful at first, but it's necessary to get your range of motion back as soon as possible. Please see today's exercise to help you stay on track. Don't forget to ice!",
          "start": 70
        },
        {
          "end": 87,
          "message": "Good job on the progress. We need to start working on bending and extending the knee. The goal is to have your knee bent to 90 degrees by Day 12 and 0 degrees by Day 10.",
          "start": 74
        },
        {
          "end": 87,
          "message": "Keep up the good work! This first phase is critical in laying the groundwork.",
          "start": 74
        },
        {
          "end": 100,
          "message": "Your almost at the end of your first week. If you can, it's time to think about tapering down on the pain medication. Please reach out the your doctor if your pain is too high to begin tapering down.",
          "start": 87
        },
        {
          "end": 100,
          "message": "Your almost at the end of your first week. If you can, it's time to think about tapering down on the pain medication. Please reach out the your doctor if your pain is too high to begin tapering down.",
          "start": 87
        },
        {
          "end": 120,
          "message": "Tomorrow is your first post-surgery doctor appointment. The doctor will be looking at your leg flexion and extension, and reviewing the swelling and incision.",
          "start": 100
        },
        {
          "end": 120,
          "message": "Remember to stretch your quad today after you complete your exercise.",
          "start": 100
        },
        {
          "end": 138,
          "message": "Today you should have reached full leg extension. Not quite there yet? Don't worry, that's not uncommon. Try these additional excercises to help get you there.",
          "start": 120
        },
        {
          "end": 138,
          "message": "Keep up the good work! This first phase is critical in laying the groundwork.",
          "start": 120
        },
        {
          "end": 159,
          "message": "Today you should be able to bend your knee to 90 degrees. Have you reached this milestone? If not, no need to worry. Here are some more exercises to help get you there.",
          "start": 138
        },
        {
          "end": 159,
          "message": "Today you should be able to bend your knee to 90 degrees. Have you reached this milestone? If not, no need to worry. Here are some more exercises to help get you there.",
          "start": 138
        },
        {
          "end": 170,
          "message": "You survived your first 2 weeks post-ACL surgery. The hardest part is over, but it's still a long road ahead. Don't give up! Here are some inspirational stories to help you feel motivated.",
          "start": 159
        },
        {
          "end": 170,
          "message": "You survived your first 2 weeks post-ACL surgery. The hardest part is over, but it's still a long road ahead. Don't give up! Here are some inspirational stories to help you feel motivated.",
          "start": 159
        },
        {
          "end": 197,
          "message": "Keep up the good work! This first phase is critical in laying the groundwork.",
          "start": 170
        },
        {
          "end": 197,
          "message": "Remember to stretch your quad today after you complete your exercise.",
          "start": 170
        },
        {
          "end": 226,
          "message": "You have about a week left, these exercises should start to feel quite a bit easier!",
          "start": 197
        },
        {
          "end": 226,
          "message": "You have about a week left, these exercises should start to feel quite a bit easier!",
          "start": 197
        },
        {
          "end": 242,
          "message": "Only a few more days in this phase, stay consistent!",
          "start": 226
        },
        null,
        {
          "end": 287,
          "message": "It's been 3 weeks, you should start to feel like your making some solid progress towards regaining mobility.",
          "start": 242
        },
        {
          "message": "Congratulations on reaching Phase 2 of your ACL Recovery. You can expect to feel some soreness still. We will be working through a few exercises and stetches today."
        }
      ],
      "phaseEndDay": [
        null,
        21,
        42,
        84,
        85,
        86,
        87
      ],
      "phases": [
        null,
        "Early Motion and Muscle Activation",
        "Balancing and Normal Gate",
        "Early Strengthening and Conditioning",
        "Advanced Strengthening and Conditioning",
        "Plyometrics and Conditioning",
        "Advanced Sports and Functional Training"
      ],
      "videoUrls": [
        "7TAslg8p2Vo",
        "QzVdEyyIiu4",
        "M9thyTdrYxw",
        "l8kzoAx8VkU",
        "zaFv0qNjSs0",
        "ZWu9MSC6WMw"
      ]
    }
  },
  "survey": {
    "day1": {
      "completedHtml": "<h3>Thank you for completing the check-in survey.</h3> <h5>Remember to contact your doctor if you have any concerns about your recovery.</h5>",
      "completedHtmlOnCondition": [
        {
          "expression": "{pain_rating} <= 3",
          "html": "<h3>Please contact your doctor to discuss your pain.</h3>"
        },
        {
          "expression": "{nps_score} > 3",
          "html": "<h3>Thank you for completing the check-in survey.</h3> <h5>Remember to contact your doctor if you have any concerns about your recovery.</h5>"
        }
      ],
      "pages": [
        {
          "elements": [
            {
              "isRequired": true,
              "maxRateDescription": "Unbearable pain",
              "minRateDescription": "No pain",
              "name": "pain_rating",
              "rateMax": 10,
              "rateMin": 1,
              "title": "What is your pain level today on a scale from 1 to 10?",
              "type": "rating"
            },
            {
              "choices": [
                "Yes",
                " No"
              ],
              "colCount": 1,
              "isRequired": true,
              "name": "concerns",
              "title": "Do you have any concerns with where you are in recovery?",
              "type": "radiogroup"
            },
            {
              "isRequired": true,
              "name": "concerns_description",
              "title": "Please describe your concerns.",
              "type": "comment",
              "visibleIf": "{concerns}='Yes'"
            }
          ],
          "name": "page1"
        }
      ],
      "showQuestionNumbers": "off"
    },
    "day2": {
      "completedHtml": "<h3>Thank you for completing the check-in survey.</h3> <h5>Remember to contact your doctor if you have any concerns about your recovery.</h5>",
      "completedHtmlOnCondition": [
        {
          "expression": "{pain_rating} <= 3",
          "html": "<h3>Please contact your doctor to discuss your pain.</h3>"
        },
        {
          "expression": "{nps_score} > 3",
          "html": "<h3>Thank you for completing the check-in survey.</h3> <h5>Remember to contact your doctor if you have any concerns about your recovery.</h5>"
        }
      ],
      "pages": [
        {
          "elements": [
            {
              "isRequired": true,
              "maxRateDescription": "Unbearable pain",
              "minRateDescription": "No pain",
              "name": "pain_rating",
              "rateMax": 10,
              "rateMin": 1,
              "title": "What is your pain level today on a scale from 1 to 10?",
              "type": "rating"
            },
            {
              "choices": [
                "Yes",
                " No"
              ],
              "colCount": 1,
              "isRequired": true,
              "name": "rehab_successful",
              "title": "Were you able to complete yesterday's rehab completely?",
              "type": "radiogroup"
            },
            {
              "choices": [
                "Yes",
                " No"
              ],
              "colCount": 1,
              "isRequired": true,
              "name": "concerns",
              "title": "Do you have any concerns with where you are in recovery?",
              "type": "radiogroup"
            },
            {
              "isRequired": true,
              "name": "concerns_description",
              "title": "Please describe your concerns.",
              "type": "comment",
              "visibleIf": "{concerns}='Yes'"
            }
          ],
          "name": "page1"
        }
      ],
      "showQuestionNumbers": "off"
    }
  },
  "user": {
    "Fake-PatientData": {
      "email": "Fake-PatientData@email.com",
      "name": "Fake Patient",
      "startDate": 1646583369397,
      "surgeryType": "acl",
      "surveyResults": [
        {
          "concerns": "No",
          "pain_rating": 1,
          "rehab_successful": "Yes"
        }
      ]
    }
  }
}